angstrom/__init__.py
angstrom/angstrom.py
angstrom-0.0.4.dist-info/LICENSE.txt
angstrom-0.0.4.dist-info/METADATA
angstrom-0.0.4.dist-info/RECORD
angstrom-0.0.4.dist-info/WHEEL
angstrom-0.0.4.dist-info/top_level.txt
