Metadata-Version: 2.1
Name: angstrom
Version: 0.0.4
Summary: Tiny ORM for SQLite3
Home-page: UNKNOWN
Author: sighphyr3
Author-email: liquidwicked64@gmail.com
License: UNKNOWN
Platform: UNKNOWN
